Metadata-Version: 1.0
Name: fontmerger
Version: 0.2.1
Summary: merging font tools
Home-page: https://github.com/iij/fontmerger
Author: Internet Initiative Japan Inc
Author-email: yosinobu@iij.ad.jp
License: MIT
Platform: UNKNOWN
